{
	"configurations" : 
	[
		{
			"directories" : 
			[
				{
					"build" : ".",
					"jsonFile" : "directory-.-Debug-f5ebdc15457944623624.json",
					"minimumCMakeVersion" : 
					{
						"string" : "3.10"
					},
					"projectIndex" : 0,
					"source" : ".",
					"targetIndexes" : 
					[
						0,
						1
					]
				}
			],
			"name" : "Debug",
			"projects" : 
			[
				{
					"directoryIndexes" : 
					[
						0
					],
					"name" : "test",
					"targetIndexes" : 
					[
						0,
						1
					]
				}
			],
			"targets" : 
			[
				{
					"directoryIndex" : 0,
					"id" : "landlord::@6890427a1f51a3e7e1df",
					"jsonFile" : "target-landlord-Debug-6ce8e1668a3e22670b93.json",
					"name" : "landlord",
					"projectIndex" : 0
				},
				{
					"directoryIndex" : 0,
					"id" : "main::@6890427a1f51a3e7e1df",
					"jsonFile" : "target-main-Debug-834dedd60b0ddf686452.json",
					"name" : "main",
					"projectIndex" : 0
				}
			]
		}
	],
	"kind" : "codemodel",
	"paths" : 
	{
		"build" : "/Users/random/github-classroom/Innopolis-University-Classroom/lab-5-oop-rootint/build",
		"source" : "/Users/random/github-classroom/Innopolis-University-Classroom/lab-5-oop-rootint"
	},
	"version" : 
	{
		"major" : 2,
		"minor" : 3
	}
}
